bin/__init__.py
bin/commands.py
faasclient/__init__.py
faasclient/client.py
faasclient/exceptions.py
tests/__init__.py
tests/test_client.py
tests/test_get_auth.py
python_faasclient-0.5.0.dist-info/LICENSE
python_faasclient-0.5.0.dist-info/METADATA
python_faasclient-0.5.0.dist-info/WHEEL
python_faasclient-0.5.0.dist-info/entry_points.txt
python_faasclient-0.5.0.dist-info/top_level.txt
python_faasclient-0.5.0.dist-info/RECORD
